{
    "welcome": "Välkommen till webbappen",
    "login": "Logga in",
    "signup": "Registrera dig för ett gratis projekt",
    "dashboard": "Instrumentpanel",
    "profile": "Min profil",
    "appointments": "Bokningar",
    "notifications": "Aviseringar",
    "settings": "Inställningar",
    "logout": "Logga ut",
    "search": "Sök i våra arkiv",
    "error": "fel och det är ett allvarligt!",
    "hellocomma": "Hej Buk!",
    "key1": "splitterny nyckel",
    "hellounivers": "Hej till alla!",
    "greeting": "Hej, {name}!",
    "key": "{{what}} är {{how}}",
    "livekey": "hej världen",
    "addedKey": "Auto hämtades till Lokalise"
}